skinseg/CLAHE.py
skinseg/GLCM.py
skinseg/Image_augmentation.py
skinseg/Overlay.py
skinseg/UNet.py
skinseg/__init__.py
skinseg/bb_to_bw.py
skinseg/binarize.py
skinseg/class_divn.py
skinseg/code_lines.py
skinseg/color_clean.py
skinseg/color_to_bw.py
skinseg/dullrazor.py
skinseg/enhance.py
skinseg/find_max_lesions.py
skinseg/get_bounding_boxes.py
skinseg/marginalize.py
skinseg/mask_generator.py
skinseg/mask_overlay.py
skinseg/maskgen_using_unet.py
skinseg/metrics.py
skinseg/montage.py
skinseg/permute_channels.py
skinseg/resize_for_segmentation.py
skinseg/texture.py
skinseg/texture_helpers.py
skinseg/transformation_helpers.py
skinseg/union.py
skinseg/utils.py
skinseg-0.0.1.dist-info/LICENSE
skinseg-0.0.1.dist-info/METADATA
skinseg-0.0.1.dist-info/WHEEL
skinseg-0.0.1.dist-info/top_level.txt
skinseg-0.0.1.dist-info/RECORD
