Metadata-Version: 2.1
Name: skinseg
Version: 0.0.1
Summary: Contains tools for segmentation of skin lesion images. A prebuilt unsupervised Segmentation model and various helper functions to increase the efficacy of segmentation. Includes tools to visualise, compare, experiment with different image configurations and segmentation types. Tools can be used in cascade to the mask generator or independently. Feel free to play around with.
Author-email: DevBhuyan <devvjiit.bhuyan@gmail.com>
Project-URL: Homepage, https://github.com/DevBhuyan/Unsup-Segmentation/
Project-URL: Bug Tracker, https://github.com/DevBhuyan/Unsup-Segmentation/issues
Classifier: Programming Language :: Python :: 3
Classifier: License :: OSI Approved :: MIT License
Classifier: Operating System :: OS Independent
Requires-Python: >=3.7
License-File: LICENSE
